README.rst
setup.py
antenna/__init__.py
sqs_antenna.egg-info/PKG-INFO
sqs_antenna.egg-info/SOURCES.txt
sqs_antenna.egg-info/dependency_links.txt
sqs_antenna.egg-info/entry_points.txt
sqs_antenna.egg-info/not-zip-safe
sqs_antenna.egg-info/requires.txt
sqs_antenna.egg-info/top_level.txt