Metadata-Version: 1.1
Name: sqs-antenna
Version: 0.1.3
Summary: Command-line tool that executes a command for each SQS message it receives.
Home-page: http://github.com/newslynx/sqs-antenna/tree/master
Author: Stijn Debrouwere
Author-email: stijn@stdout.be
License: ISC
Platform: UNKNOWN
Classifier: Development Status :: 4 - Beta
Classifier: Intended Audience :: Developers
Classifier: License :: OSI Approved :: MIT License
Classifier: Operating System :: OS Independent
Classifier: Programming Language :: Python
